nsstools/__init__.py
nsstools/classes.py
nsstools-0.1.12.dist-info/METADATA
nsstools-0.1.12.dist-info/WHEEL
nsstools-0.1.12.dist-info/top_level.txt
nsstools-0.1.12.dist-info/RECORD
