Metadata-Version: 2.1
Name: nsstools
Version: 0.1.12
Summary: Tools for calculate campbell and covmat from Gaia CU4 sources
Home-page: https://gitlab.obspm.fr/gaia/nsstools.git
Author: Nicolas Leclerc, Carine Babusiaux, Jean-Louis Halbwachs
Author-email: gaia.project@obspm.fr
License: CeCILL-2.1
Platform: UNKNOWN
Classifier: Programming Language :: Python :: 3
Classifier: Development Status :: 5 - Production/Stable
Classifier: Programming Language :: Python :: 3.5
Classifier: Topic :: Scientific/Engineering :: Astronomy
Requires-Python: >=3.5
Requires-Dist: numpy
Requires-Dist: pandas
